odoo/addons/purchase_split_wizard/README.rst
odoo/addons/purchase_split_wizard/__init__.py
odoo/addons/purchase_split_wizard/__manifest__.py
odoo/addons/purchase_split_wizard/i18n/es.po
odoo/addons/purchase_split_wizard/models/__init__.py
odoo/addons/purchase_split_wizard/models/purchase_order.py
odoo/addons/purchase_split_wizard/models/purchase_order_line.py
odoo/addons/purchase_split_wizard/models/stock_rule.py
odoo/addons/purchase_split_wizard/readme/CONTRIBUTORS.md
odoo/addons/purchase_split_wizard/readme/DESCRIPTION.md
odoo/addons/purchase_split_wizard/readme/ROADMAP.md
odoo/addons/purchase_split_wizard/readme/USAGE.md
odoo/addons/purchase_split_wizard/security/ir.model.access.csv
odoo/addons/purchase_split_wizard/static/description/icon.png
odoo/addons/purchase_split_wizard/static/description/index.html
odoo/addons/purchase_split_wizard/tests/__init__.py
odoo/addons/purchase_split_wizard/tests/test_purchase_split_wizard.py
odoo/addons/purchase_split_wizard/views/purchase_order_views.xml
odoo/addons/purchase_split_wizard/wizards/__init__.py
odoo/addons/purchase_split_wizard/wizards/purchase_split_wizard.py
odoo/addons/purchase_split_wizard/wizards/purchase_split_wizard_views.xml
odoo_addon_purchase_split_wizard-16.0.1.1.0.dist-info/METADATA
odoo_addon_purchase_split_wizard-16.0.1.1.0.dist-info/WHEEL
odoo_addon_purchase_split_wizard-16.0.1.1.0.dist-info/top_level.txt
odoo_addon_purchase_split_wizard-16.0.1.1.0.dist-info/RECORD
