Metadata-Version: 2.1
Name: odoo-addon-purchase_split_wizard
Version: 16.0.1.1.0
Requires-Python: >=3.10
Requires-Dist: odoo-addon-account_payment_purchase>=16.0dev,<16.1dev
Requires-Dist: odoo-addon-purchase_order_archive_draft>=16.0dev,<16.1dev
Requires-Dist: odoo>=16.0a,<16.1dev
Summary: Wizard to split purchase orders into multiple ones
Home-page: https://github.com/sygel-technology/sy-purchase-workflow
License: AGPL-3
Author: Sygel, Odoo Community Association (OCA)
Author-email: support@odoo-community.org
Classifier: Programming Language :: Python
Classifier: Framework :: Odoo
Classifier: Framework :: Odoo :: 16.0
Classifier: License :: OSI Approved :: GNU Affero General Public License v3
